hpimdm/Config.py
hpimdm/Interface.py
hpimdm/InterfaceHPIM.py
hpimdm/InterfaceHPIM6.py
hpimdm/Kernel.py
hpimdm/Main.py
hpimdm/Neighbor.py
hpimdm/ReliableMsgTransmission.py
hpimdm/Run.py
hpimdm/TestLogger.py
hpimdm/UnicastRouting.py
hpimdm/__init__.py
hpimdm/utils.py
hpimdm/daemon/Daemon.py
hpimdm/daemon/__init__.py
hpimdm/packet/Packet.py
hpimdm/packet/PacketHPIMAck.py
hpimdm/packet/PacketHPIMHeader.py
hpimdm/packet/PacketHPIMHello.py
hpimdm/packet/PacketHPIMHelloOptions.py
hpimdm/packet/PacketHPIMIamUpstream.py
hpimdm/packet/PacketHPIMInterest.py
hpimdm/packet/PacketHPIMNotUpstream.py
hpimdm/packet/PacketHPIMSync.py
hpimdm/packet/PacketIpHeader.py
hpimdm/packet/PacketPayload.py
hpimdm/packet/ReceivedPacket.py
hpimdm/packet/__init__.py
hpimdm/rwlock/RWLock.py
hpimdm/rwlock/__init__.py
hpimdm/tree/KernelEntry.py
hpimdm/tree/KernelEntryInterface.py
hpimdm/tree/__init__.py
hpimdm/tree/assert_state.py
hpimdm/tree/data_packets_socket.py
hpimdm/tree/downstream_state.py
hpimdm/tree/hpim_globals.py
hpimdm/tree/local_membership.py
hpimdm/tree/metric.py
hpimdm/tree/non_root_state_machine.py
hpimdm/tree/root_state_machine.py
hpimdm/tree/tree_if_non_root.py
hpimdm/tree/tree_if_root.py
hpimdm/tree/tree_if_root_originator.py
hpimdm/tree/tree_interface.py
hpimdm/tree/tree_state.py
hpim_dm-1.5.1.dist-info/LICENSE
hpim_dm-1.5.1.dist-info/METADATA
hpim_dm-1.5.1.dist-info/WHEEL
hpim_dm-1.5.1.dist-info/entry_points.txt
hpim_dm-1.5.1.dist-info/top_level.txt
hpim_dm-1.5.1.dist-info/RECORD
