Metadata-Version: 2.1
Name: hpim-dm
Version: 1.5.1
Summary: HPIM-DM protocol
Home-page: http://github.com/pedrofran12/hpim_dm
Author: Pedro Oliveira
Author-email: pedro.francisco.oliveira@tecnico.ulisboa.pt
License: MIT
Keywords: HPIM-DM Multicast Routing Protocol HPIM Dense-Mode Router IPv4 IPv6
Platform: any
Classifier: Development Status :: 4 - Beta
Classifier: Environment :: Console
Classifier: Intended Audience :: Information Technology
Classifier: Topic :: System :: Networking
Classifier: License :: OSI Approved :: MIT License
Classifier: Natural Language :: English
Classifier: Operating System :: OS Independent
Classifier: Programming Language :: Python
Classifier: Programming Language :: Python :: 3
Classifier: Programming Language :: Python :: 3.3
Classifier: Programming Language :: Python :: 3.4
Classifier: Programming Language :: Python :: 3.5
Classifier: Programming Language :: Python :: 3.6
Classifier: Programming Language :: Python :: 3.7
Classifier: Programming Language :: Python :: 3.8
Classifier: Programming Language :: Python :: 3.9
Requires-Python: >=3.3
Requires-Dist: PrettyTable
Requires-Dist: netifaces
Requires-Dist: ipaddress
Requires-Dist: pyroute2
Requires-Dist: py-mld (==1.0)
Requires-Dist: igmp (==1.0.2)
